{
  "version": "7",
  "dialect": "postgresql",
  "entries": [
    {
      "idx": 0,
      "version": "7",
      "when": 1781369147949,
      "tag": "0000_robust_vance_astro",
      "breakpoints": true
    },
    {
      "idx": 1,
      "version": "7",
      "when": 1781908539441,
      "tag": "0001_silly_captain_midlands",
      "breakpoints": true
    },
    {
      "idx": 2,
      "version": "7",
      "when": 1781958582634,
      "tag": "0002_busy_mesmero",
      "breakpoints": true
    }
  ]
}